Workbook

Sheet 表1（IT界面）
A1: 物料开头 | B1: 是否维护 | C1: 工厂 | D1: 跨工厂物料状态 | E1: MS | F1: 在工厂级别将物料标记为删除 | G1: 物料 | H1: BMR | I1: 物料描述 | J1: 生产厂商 | K1: 已创建 | L1: 创建时间 | M1: 备注2 | N1: 创建者 | O1: MTyp | P1: 物料类型 | Q1: 物料组 | R1: 物料组 | S1: 基本计量单位 | T1: 行业标准描述 | U1: 大小/量纲 | V1: 片型 | W1: 包装形式 | X1: 包装规格 | Y1: 毛重 | Z1: WUn | AA1: 净重 | AB1: WUn | AC1: SC | AD1: 存储条件 | AE1: SLife | AF1: RShLi | AG1: 期间标识 | AH1: 货架存放期过期日期的期间标识 | AI1: 市场 | AJ1: 外部物料组 | AK1: 外部物料组 | AL1: NDC国家药品监管码 | AM1: ANDA代码 | AN1: 标准托的数量 | AO1: 参考标准 | AP1: 货号 | AQ1: 中包装规格 | AR1: 中包装规格单位 | AS1: 最大包装规格 | AT1: 最大包装规格单位 | AU1: 最小包装规格 | AV1: 最小包装规格单位 | AW1: 舍入规则 | AX1: 利润中心 | AY1: 备注1 | AZ1: 备注3 | BA1: 备注4 | BB1: 备注5 | BC1: 基本视图K | BD1: 分类视图C | BE1: 仓储视图L | BF1: 成本视图G | BG1: 会计视图B | BH1: 采购视图E | BI1: 质量视图Q | BJ1: MRP视图D | BK1: 销售视图V | BL1: 工作视图A | BM1: 维护状态
A2: =LEN(G2)&LEFT(G2,1) -> 64 | B2: 是 | C2: 5300 | D2: 02 | F2: 否 | G2: 400976 | H2: X | I2: 盐酸米诺环素胶囊/50mg/中国 | J2: 浙江昌海制药有限公司 | K2: 45285 | L2: 0.065150463 | M2: 研发 | N2: ZHENGX | O2: Z003 | P2: 华海半成品 | Q2: 310104 | R2: 制剂非无菌中间产品-胶囊 | S2: 粒 | T2: QS-T-F-023 | U2: 50mg | V2: 胶囊 | Y2: 0 | AA2: 0 | AE2: 0 | AF2: 0 | AG2: D | AH2: 天 | AI2: 中国 | AY2: 李文静 | BB2: NA | BC2: X | BD2: X | BE2: X | BH2: X | BI2: X | BM2: KCELQ
A3: =LEN(G3)&LEFT(G3,1) -> 64 | B3: 是 | C3: 5300 | D3: 02 | F3: 否 | G3: 400979 | H3: X | I3: 利奥西呱片/0.5mg/中国 | J3: 江苏天晟药业股份有限公司 | K3: 45285 | L3: 0.10648148 | M3: 研发 | N3: ZHENGX | O3: Z003 | P3: 华海半成品 | Q3: 310103 | R3: 制剂非无菌中间产品-片子 | S3: 片 | T3: QS-T-F-022 | U3: 0.5mg | V3: 圆形 | Y3: 0 | AA3: 0 | AE3: 0 | AF3: 0 | AG3: D | AH3: 天 | AI3: 中国 | AY3: 蒋智豪 | BB3: NA | BC3: X | BD3: X | BE3: X | BH3: X | BI3: X | BM3: KCELQ
A4: =LEN(G4)&LEFT(G4,1) -> 64 | B4: 是 | C4: 5300 | D4: 02 | F4: 否 | G4: 400983 | H4: X | I4: 利奥西呱片/1mg/中国 | K4: 45285 | L4: 0.11353009 | M4: 研发 | N4: ZHENGX | O4: Z003 | P4: 华海半成品 | Q4: 310103 | R4: 制剂非无菌中间产品-片子 | S4: 片 | T4: QS-T-F-022 | U4: 1mg | V4: 圆形 | Y4: 0 | AA4: 0 | AE4: 0 | AF4: 0 | AG4: D | AH4: 天 | AY4: 蒋智豪 | BB4: NA | BC4: X | BD4: X | BE4: X | BH4: X | BI4: X | BM4: KCELQ
A5: =LEN(G5)&LEFT(G5,1) -> 64 | B5: 是 | C5: 5300 | D5: 02 | F5: 否 | G5: 400985 | H5: X | I5: 利奥西呱片/2.5mg/中国 | J5: 江苏天晟药业股份有限公司 | K5: 45285 | L5: 0.1171875 | M5: 研发 | N5: ZHENGX | O5: Z003 | P5: 华海半成品 | Q5: 310103 | R5: 制剂非无菌中间产品-片子 | S5: 片 | T5: QS-T-F-022 | U5: 2.5mg | V5: 圆形 | Y5: 0 | AA5: 0 | AE5: 0 | AF5: 0 | AG5: D | AH5: 天 | AY5: 蒋智豪 | BB5: NA | BC5: X | BD5: X | BE5: X | BH5: X | BI5: X | BM5: KCELQ
A6: =LEN(G6)&LEFT(G6,1) -> 61 | B6: 是 | C6: 5300 | D6: 01 | F6: 否 | G6: 101903 | H6: X | I6: 明胶空心胶囊/4#/ChP | J6: 绍兴康可胶囊有限公司 | K6: 45285 | L6: 0.26359954 | M6: 项目 | N6: ZHENGX | O6: Z001 | P6: 华海原辅料 | Q6: 120101 | R6: 固体辅料-一般 | S6: 千粒 | T6: QS-T-E-033 | U6: 4# | Y6: 0 | AA6: 0 | AE6: 0 | AF6: 0 | AG6: D | AH6: 天 | AI6: 中国 | AL6: ChP | AY6: 李文静 | BB6: 全白 | BC6: X | BD6: X | BE6: X | BH6: X | BI6: X | BM6: KCELQ
A7: =LEN(G7)&LEFT(G7,1) -> 64 | B7: 是 | C7: 5300 | D7: 02 | F7: 否 | G7: 400988 | H7: X | I7: 盐酸曲唑酮片/25mg/中国 | J7: Mylan Laboratories Limited | K7: 45293 | L7: 0.041770833 | M7: 研发 | N7: ZHENGX | O7: Z003 | P7: 华海半成品 | Q7: 310103 | R7: 制剂非无菌中间产品-片子 | S7: 片 | T7: QS-T-F-024 | U7: 25mg | V7: 圆形 | Y7: 0 | AA7: 0 | AE7: 0 | AF7: 0 | AG7: D | AH7: 天 | AI7: 中国 | AY7: 何敏迪 | BB7: NA | BC7: X | BD7: X | BE7: X | BI7: X | BM7: KCLQ
A8: =LEN(G8)&LEFT(G8,1) -> 64 | B8: 是 | C8: 5300 | D8: 02 | F8: 否 | G8: 400992 | H8: X | I8: 盐酸曲唑酮片/50mg/中国 | K8: 45293 | L8: 0.046759259 | M8: 研发 | N8: ZHENGX | O8: Z003 | P8: 华海半成品 | Q8: 310103 | R8: 制剂非无菌中间产品-片子 | S8: 片 | T8: QS-T-F-024 | U8: 50mg | V8: 圆形 | Y8: 0 | AA8: 0 | AE8: 0 | AF8: 0 | AG8: D | AH8: 天 | AY8: 何敏迪 | BB8: NA | BC8: X | BD8: X | BE8: X | BI8: X | BM8: KCLQ
A9: =LEN(G9)&LEFT(G9,1) -> 0 | B9: 是
A10: =LEN(G10)&LEFT(G10,1) -> 0 | B10: 是
A11: =LEN(G11)&LEFT(G11,1) -> 0 | B11: 是
A12: =LEN(G12)&LEFT(G12,1) -> 0 | B12: 是
A13: =LEN(G13)&LEFT(G13,1) -> 0 | B13: 是
A14: =LEN(G14)&LEFT(G14,1) -> 0 | B14: 是
A15: =LEN(G15)&LEFT(G15,1) -> 0 | B15: 是
A16: =LEN(G16)&LEFT(G16,1) -> 0 | B16: 是
A17: =LEN(G17)&LEFT(G17,1) -> 0 | B17: 是
A18: =LEN(G18)&LEFT(G18,1) -> 0 | B18: 是
A19: =LEN(G19)&LEFT(G19,1) -> 0 | B19: 是
A20: =LEN(G20)&LEFT(G20,1) -> 0 | B20: 是
... A993: =LEN(G993)&LEFT(G993,1) -> 0 | B993: 是
A995: 61
A996: 62
A997: 63
A998: 64
A999: 65
A1000: 71
A1002: 61
A1003: 62
A1004: 63
A1005: 64
A1006: 65
A1007: 71

Sheet 表2（QC界面）
A1: 物料 | B1: BMR | C1: 物料描述 | D1: 市场 | E1: 备注1 | F1: 备注2 | G1: 生产厂家 | H1: 单位 | J1: 检测周期 （天）
A2: 物料开头 | B2: (多项)
A4: 计数项:工厂
A5: 物料 | B5: BMR | C5: 物料描述 | D5: 市场 | E5: 备注1 | F5: 备注2 | G5: 生产厂商 | H5: 基本计量单位 | I5: 汇总
A6: 101903 | B6: X | C6: 明胶空心胶囊/4#/ChP | D6: 中国 | E6: 李文静 | F6: 项目 | G6: 绍兴康可胶囊有限公司 | H6: 千粒 | I6: 1 | J6: 26

Sheet 表3（采购界面）
A1: 物料 | B1: BMR | C1: 物料描述 | D1: 市场 | E1: 备注1 | F1: 备注2 | G1: 生产厂家 | H1: 单位 | J1: 最小批量大小 | K1: 舍入值 | L1: 计划交货时间（天）
A2: 物料开头 | B2: (多项)
A4: 计数项:工厂
A5: 物料 | B5: BMR | C5: 物料描述 | D5: 市场 | E5: 备注1 | F5: 备注2 | G5: 生产厂商 | H5: 基本计量单位 | I5: 汇总
A6: 101903 | B6: X | C6: 明胶空心胶囊/4#/ChP | D6: 中国 | E6: 李文静 | F6: 项目 | G6: 绍兴康可胶囊有限公司 | H6: 千粒 | I6: 1 | J6: 500 | L6: 30
A7: 1

Sheet 表4（运营界面）
A1: 物料 | B1: BMR | C1: 物料描述 | D1: 市场 | E1: 备注1 | F1: 备注2 | G1: 生产厂家 | H1: 单位 | J1: MRP控制者 | K1: MRP类型 | L1: 批量程序 | M1: 固定批量 | N1: 再订货点 | O1: 安全库存 | P1: 批量大小 | Q1: 舍入值 | R1: 采购类型 | S1: 收货处理时间 | T1: 计划交货时间 | U1: MRP区域 | V1: 反冲 | W1: 批量输入 | X1: 自制生产时间 | Y1: 策略组 | Z1: 综合MRP | AA1: 消耗模式 | AB1: 向前消耗期间 | AC1: 向后消耗期间 | AD1: 独立/集中 | AE1: 计划的时界 | AF1: 生产调度员 | AG1: 生产计划参数文件
A2: 是否维护 | B2: 是
A4: 计数项:工厂
A5: 物料 | B5: BMR | C5: 物料描述 | D5: 市场 | E5: 备注1 | F5: 备注2 | G5: 生产厂商 | H5: 基本计量单位 | I5: 汇总
A6: 101903 | B6: X | C6: 明胶空心胶囊/4#/ChP | D6: 中国 | E6: 李文静 | F6: 项目 | G6: 绍兴康可胶囊有限公司 | H6: 千粒 | I6: 1 | J6: Y01 | K6: =_xlfn.IFS(AND(LEFT(A6,1)="4",D6="中国"),"ND",AND(LEFT(A6,1)="5",D6="中国"),"ND",AND(LEFT(A6,1)="5",D6<>"中国"),"M2",A6="","",A6<>"","PD") -> PD | L6: =_xlfn.IFS(LEFT(A6)="1","MB",LEFT(A6)="2","WB",LEFT(A6)="3","WB",AND(LEFT(A6)="4",D6<>"中国",J6<>"Y01"),"FX",A6<>"","EX",A6="","") -> MB | M6: =IF(OR(L6="FX",L6=""),"","NA") -> NA | N6: =IF(A6="","","NA") -> NA | O6: =IF(OR(LEFT(A6,1)="4",LEFT(A6,1)="5"),"NA","") | P6: =IF(A6="","",IFERROR(VLOOKUP(A6,'表3（采购界面）'!A:J,10,0),"NA")) -> 500 | Q6: =IF(A6="","",IFERROR(VLOOKUP(A6,'表3（采购界面）'!A:Z,11,0),"NA")) -> 0 | R6: =IF(A6="","",IF(OR(LEFT(A6,1)="1",LEFT(A6,1)="2",LEFT(A6,1)="3"),"F","E")) -> F | S6: =_xlfn.IFS(LEFT(A6,1)="5",VLOOKUP(A6,'表2（QC界面）'!A:J,10,0)+2,LEFT(A6,1)="4",0,AND(LEFT(A6,1)="1",J6<>"Y01"),VLOOKUP(A6,'表2（QC界面）'!A:J,10,0)+24,A6<>0,VLOOKUP(A6,'表2（QC界面）'!A:J,10,0)+4) -> 30 | T6: =IF(OR(LEFT(A6,1)="4",LEFT(A6,1)="5"),"NA",VLOOKUP(A6,'表3（采购界面）'!A:L,12,0)) -> 30 | U6: =IF(A6="","","5000-1") -> 5000-1 | V6: =_xlfn.IFS(LEFT(A6,1)="1",2,LEFT(A6,1)="2",1,LEFT(A6,1)="4",1,A6<>0,"NA") -> 2 | W6: =IF(LEFT(A6,1)="4",1,"NA") -> NA | X6: =_xlfn.IFS(LEFT(A6,1)="4",25,LEFT(A6,1)="5",10,A6<>0,"NA") -> NA | Y6: =_xlfn.IFS(LEFT(A6,1)="4",10,AND(LEFT(A6,1)="5",D6="中国"),11,LEFT(A6,1)="5",50,A6<>0,"NA") -> NA | Z6: =IF(AND(LEFT(A6,1)="5",D6="中国"),2,"NA") -> NA | AA6: =_xlfn.IFS(AND(LEFT(A6,1)="5",D6="中国"),2,LEFT(A6,1)="5",1,A6<>0,"NA") -> NA | AB6: =_xlfn.IFS(AND(LEFT(A6,1)="5",D6="中国"),30,LEFT(A6,1)="5",999,A6<>0,"NA") -> NA | AC6: =AB6 -> NA | AD6: =IF(LEFT(A6,1)="5","NA",2) -> 2 | AE6: =_xlfn.IFS(AND(LEFT(A6,1)="5",D6="中国"),1,LEFT(A6,1)="5",60,A6<>0,"NA") -> NA | AF6: =IF(OR(LEFT(A6,1)="4",LEFT(A6,1)="5"),J6,"NA") -> NA | AG6: =IF(OR(LEFT(A6,1)="4",LEFT(A6,1)="5"),"ZJ01","NA") -> NA
A7: 400976 | B7: X | C7: 盐酸米诺环素胶囊/50mg/中国 | D7: 中国 | E7: 李文静 | F7: 研发 | G7: 浙江昌海制药有限公司 | H7: 粒 | I7: 1 | J7: Y01 | K7: =_xlfn.IFS(AND(LEFT(A7,1)="4",D7="中国"),"ND",AND(LEFT(A7,1)="5",D7="中国"),"ND",AND(LEFT(A7,1)="5",D7<>"中国"),"M2",A7="","",A7<>"","PD") -> ND | L7: =_xlfn.IFS(LEFT(A7)="1","MB",LEFT(A7)="2","WB",LEFT(A7)="3","WB",AND(LEFT(A7)="4",D7<>"中国",J7<>"Y01"),"FX",A7<>"","EX",A7="","") -> EX | M7: =IF(OR(L7="FX",L7=""),"","NA") -> NA | N7: =IF(A7="","","NA") -> NA | O7: =IF(OR(LEFT(A7,1)="4",LEFT(A7,1)="5"),"NA","") -> NA | P7: =IF(A7="","",IFERROR(VLOOKUP(A7,'表3（采购界面）'!A:J,10,0),"NA")) -> NA | Q7: =IF(A7="","",IFERROR(VLOOKUP(A7,'表3（采购界面）'!A:Z,11,0),"NA")) -> NA | R7: =IF(A7="","",IF(OR(LEFT(A7,1)="1",LEFT(A7,1)="2",LEFT(A7,1)="3"),"F","E")) -> E | S7: =_xlfn.IFS(LEFT(A7,1)="5",VLOOKUP(A7,'表2（QC界面）'!A:J,10,0)+2,LEFT(A7,1)="4",0,AND(LEFT(A7,1)="1",J7<>"Y01"),VLOOKUP(A7,'表2（QC界面）'!A:J,10,0)+24,A7<>0,VLOOKUP(A7,'表2（QC界面）'!A:J,10,0)+4) -> 0 | T7: =IF(OR(LEFT(A7,1)="4",LEFT(A7,1)="5"),"NA",VLOOKUP(A7,'表3（采购界面）'!A:L,12,0)) -> NA | U7: =IF(A7="","","5000-1") -> 5000-1 | V7: =_xlfn.IFS(LEFT(A7,1)="1",2,LEFT(A7,1)="2",1,LEFT(A7,1)="4",1,A7<>0,"NA") -> 1 | W7: =IF(LEFT(A7,1)="4",1,"NA") -> 1 | X7: =_xlfn.IFS(LEFT(A7,1)="4",25,LEFT(A7,1)="5",10,A7<>0,"NA") -> 25 | Y7: =_xlfn.IFS(LEFT(A7,1)="4",10,AND(LEFT(A7,1)="5",D7="中国"),11,LEFT(A7,1)="5",50,A7<>0,"NA") -> 10 | Z7: =IF(AND(LEFT(A7,1)="5",D7="中国"),2,"NA") -> NA | AA7: =_xlfn.IFS(AND(LEFT(A7,1)="5",D7="中国"),2,LEFT(A7,1)="5",1,A7<>0,"NA") -> NA | AB7: =_xlfn.IFS(AND(LEFT(A7,1)="5",D7="中国"),30,LEFT(A7,1)="5",999,A7<>0,"NA") -> NA | AC7: =AB7 -> NA | AD7: =IF(LEFT(A7,1)="5","NA",2) -> 2 | AE7: =_xlfn.IFS(AND(LEFT(A7,1)="5",D7="中国"),1,LEFT(A7,1)="5",60,A7<>0,"NA") -> NA | AF7: =IF(OR(LEFT(A7,1)="4",LEFT(A7,1)="5"),J7,"NA") -> Y01 | AG7: =IF(OR(LEFT(A7,1)="4",LEFT(A7,1)="5"),"ZJ01","NA") -> ZJ01
A8: 400979 | B8: X | C8: 利奥西呱片/0.5mg/中国 | D8: 中国 | E8: 蒋智豪 | F8: 研发 | G8: 江苏天晟药业股份有限公司 | H8: 片 | I8: 1 | J8: Y01 | K8: =_xlfn.IFS(AND(LEFT(A8,1)="4",D8="中国"),"ND",AND(LEFT(A8,1)="5",D8="中国"),"ND",AND(LEFT(A8,1)="5",D8<>"中国"),"M2",A8="","",A8<>"","PD") -> ND | L8: =_xlfn.IFS(LEFT(A8)="1","MB",LEFT(A8)="2","WB",LEFT(A8)="3","WB",AND(LEFT(A8)="4",D8<>"中国",J8<>"Y01"),"FX",A8<>"","EX",A8="","") -> EX | M8: =IF(OR(L8="FX",L8=""),"","NA") -> NA | N8: =IF(A8="","","NA") -> NA | O8: =IF(OR(LEFT(A8,1)="4",LEFT(A8,1)="5"),"NA","") -> NA | P8: =IF(A8="","",IFERROR(VLOOKUP(A8,'表3（采购界面）'!A:J,10,0),"NA")) -> NA | Q8: =IF(A8="","",IFERROR(VLOOKUP(A8,'表3（采购界面）'!A:Z,11,0),"NA")) -> NA | R8: =IF(A8="","",IF(OR(LEFT(A8,1)="1",LEFT(A8,1)="2",LEFT(A8,1)="3"),"F","E")) -> E | S8: =_xlfn.IFS(LEFT(A8,1)="5",VLOOKUP(A8,'表2（QC界面）'!A:J,10,0)+2,LEFT(A8,1)="4",0,AND(LEFT(A8,1)="1",J8<>"Y01"),VLOOKUP(A8,'表2（QC界面）'!A:J,10,0)+24,A8<>0,VLOOKUP(A8,'表2（QC界面）'!A:J,10,0)+4) -> 0 | T8: =IF(OR(LEFT(A8,1)="4",LEFT(A8,1)="5"),"NA",VLOOKUP(A8,'表3（采购界面）'!A:L,12,0)) -> NA | U8: =IF(A8="","","5000-1") -> 5000-1 | V8: =_xlfn.IFS(LEFT(A8,1)="1",2,LEFT(A8,1)="2",1,LEFT(A8,1)="4",1,A8<>0,"NA") -> 1 | W8: =IF(LEFT(A8,1)="4",1,"NA") -> 1 | X8: =_xlfn.IFS(LEFT(A8,1)="4",25,LEFT(A8,1)="5",10,A8<>0,"NA") -> 25 | Y8: =_xlfn.IFS(LEFT(A8,1)="4",10,AND(LEFT(A8,1)="5",D8="中国"),11,LEFT(A8,1)="5",50,A8<>0,"NA") -> 10 | Z8: =IF(AND(LEFT(A8,1)="5",D8="中国"),2,"NA") -> NA | AA8: =_xlfn.IFS(AND(LEFT(A8,1)="5",D8="中国"),2,LEFT(A8,1)="5",1,A8<>0,"NA") -> NA | AB8: =_xlfn.IFS(AND(LEFT(A8,1)="5",D8="中国"),30,LEFT(A8,1)="5",999,A8<>0,"NA") -> NA | AC8: =AB8 -> NA | AD8: =IF(LEFT(A8,1)="5","NA",2) -> 2 | AE8: =_xlfn.IFS(AND(LEFT(A8,1)="5",D8="中国"),1,LEFT(A8,1)="5",60,A8<>0,"NA") -> NA | AF8: =IF(OR(LEFT(A8,1)="4",LEFT(A8,1)="5"),J8,"NA") -> Y01 | AG8: =IF(OR(LEFT(A8,1)="4",LEFT(A8,1)="5"),"ZJ01","NA") -> ZJ01
A9: 400983 | B9: X | C9: 利奥西呱片/1mg/中国 | E9: 蒋智豪 | F9: 研发 | H9: 片 | I9: 1 | J9: Y01 | K9: =_xlfn.IFS(AND(LEFT(A9,1)="4",D9="中国"),"ND",AND(LEFT(A9,1)="5",D9="中国"),"ND",AND(LEFT(A9,1)="5",D9<>"中国"),"M2",A9="","",A9<>"","PD") -> PD | L9: =_xlfn.IFS(LEFT(A9)="1","MB",LEFT(A9)="2","WB",LEFT(A9)="3","WB",AND(LEFT(A9)="4",D9<>"中国",J9<>"Y01"),"FX",A9<>"","EX",A9="","") -> EX | M9: =IF(OR(L9="FX",L9=""),"","NA") -> NA | N9: =IF(A9="","","NA") -> NA | O9: =IF(OR(LEFT(A9,1)="4",LEFT(A9,1)="5"),"NA","") -> NA | P9: =IF(A9="","",IFERROR(VLOOKUP(A9,'表3（采购界面）'!A:J,10,0),"NA")) -> NA | Q9: =IF(A9="","",IFERROR(VLOOKUP(A9,'表3（采购界面）'!A:Z,11,0),"NA")) -> NA | R9: =IF(A9="","",IF(OR(LEFT(A9,1)="1",LEFT(A9,1)="2",LEFT(A9,1)="3"),"F","E")) -> E | S9: =_xlfn.IFS(LEFT(A9,1)="5",VLOOKUP(A9,'表2（QC界面）'!A:J,10,0)+2,LEFT(A9,1)="4",0,AND(LEFT(A9,1)="1",J9<>"Y01"),VLOOKUP(A9,'表2（QC界面）'!A:J,10,0)+24,A9<>0,VLOOKUP(A9,'表2（QC界面）'!A:J,10,0)+4) -> 0 | T9: =IF(OR(LEFT(A9,1)="4",LEFT(A9,1)="5"),"NA",VLOOKUP(A9,'表3（采购界面）'!A:L,12,0)) -> NA | U9: =IF(A9="","","5000-1") -> 5000-1 | V9: =_xlfn.IFS(LEFT(A9,1)="1",2,LEFT(A9,1)="2",1,LEFT(A9,1)="4",1,A9<>0,"NA") -> 1 | W9: =IF(LEFT(A9,1)="4",1,"NA") -> 1 | X9: =_xlfn.IFS(LEFT(A9,1)="4",25,LEFT(A9,1)="5",10,A9<>0,"NA") -> 25 | Y9: =_xlfn.IFS(LEFT(A9,1)="4",10,AND(LEFT(A9,1)="5",D9="中国"),11,LEFT(A9,1)="5",50,A9<>0,"NA") -> 10 | Z9: =IF(AND(LEFT(A9,1)="5",D9="中国"),2,"NA") -> NA | AA9: =_xlfn.IFS(AND(LEFT(A9,1)="5",D9="中国"),2,LEFT(A9,1)="5",1,A9<>0,"NA") -> NA | AB9: =_xlfn.IFS(AND(LEFT(A9,1)="5",D9="中国"),30,LEFT(A9,1)="5",999,A9<>0,"NA") -> NA | AC9: =AB9 -> NA | AD9: =IF(LEFT(A9,1)="5","NA",2) -> 2 | AE9: =_xlfn.IFS(AND(LEFT(A9,1)="5",D9="中国"),1,LEFT(A9,1)="5",60,A9<>0,"NA") -> NA | AF9: =IF(OR(LEFT(A9,1)="4",LEFT(A9,1)="5"),J9,"NA") -> Y01 | AG9: =IF(OR(LEFT(A9,1)="4",LEFT(A9,1)="5"),"ZJ01","NA") -> ZJ01
A10: 400985 | B10: X | C10: 利奥西呱片/2.5mg/中国 | E10: 蒋智豪 | F10: 研发 | G10: 江苏天晟药业股份有限公司 | H10: 片 | I10: 1 | J10: Y01 | K10: =_xlfn.IFS(AND(LEFT(A10,1)="4",D10="中国"),"ND",AND(LEFT(A10,1)="5",D10="中国"),"ND",AND(LEFT(A10,1)="5",D10<>"中国"),"M2",A10="","",A10<>"","PD") -> PD | L10: =_xlfn.IFS(LEFT(A10)="1","MB",LEFT(A10)="2","WB",LEFT(A10)="3","WB",AND(LEFT(A10)="4",D10<>"中国",J10<>"Y01"),"FX",A10<>"","EX",A10="","") -> EX | M10: =IF(OR(L10="FX",L10=""),"","NA") -> NA | N10: =IF(A10="","","NA") -> NA | O10: =IF(OR(LEFT(A10,1)="4",LEFT(A10,1)="5"),"NA","") -> NA | P10: =IF(A10="","",IFERROR(VLOOKUP(A10,'表3（采购界面）'!A:J,10,0),"NA")) -> NA | Q10: =IF(A10="","",IFERROR(VLOOKUP(A10,'表3（采购界面）'!A:Z,11,0),"NA")) -> NA | R10: =IF(A10="","",IF(OR(LEFT(A10,1)="1",LEFT(A10,1)="2",LEFT(A10,1)="3"),"F","E")) -> E | S10: =_xlfn.IFS(LEFT(A10,1)="5",VLOOKUP(A10,'表2（QC界面）'!A:J,10,0)+2,LEFT(A10,1)="4",0,AND(LEFT(A10,1)="1",J10<>"Y01"),VLOOKUP(A10,'表2（QC界面）'!A:J,10,0)+24,A10<>0,VLOOKUP(A10,'表2（QC界面）'!A:J,10,0)+4) -> 0 | T10: =IF(OR(LEFT(A10,1)="4",LEFT(A10,1)="5"),"NA",VLOOKUP(A10,'表3（采购界面）'!A:L,12,0)) -> NA | U10: =IF(A10="","","5000-1") -> 5000-1 | V10: =_xlfn.IFS(LEFT(A10,1)="1",2,LEFT(A10,1)="2",1,LEFT(A10,1)="4",1,A10<>0,"NA") -> 1 | W10: =IF(LEFT(A10,1)="4",1,"NA") -> 1 | X10: =_xlfn.IFS(LEFT(A10,1)="4",25,LEFT(A10,1)="5",10,A10<>0,"NA") -> 25 | Y10: =_xlfn.IFS(LEFT(A10,1)="4",10,AND(LEFT(A10,1)="5",D10="中国"),11,LEFT(A10,1)="5",50,A10<>0,"NA") -> 10 | Z10: =IF(AND(LEFT(A10,1)="5",D10="中国"),2,"NA") -> NA | AA10: =_xlfn.IFS(AND(LEFT(A10,1)="5",D10="中国"),2,LEFT(A10,1)="5",1,A10<>0,"NA") -> NA | AB10: =_xlfn.IFS(AND(LEFT(A10,1)="5",D10="中国"),30,LEFT(A10,1)="5",999,A10<>0,"NA") -> NA | AC10: =AB10 -> NA | AD10: =IF(LEFT(A10,1)="5","NA",2) -> 2 | AE10: =_xlfn.IFS(AND(LEFT(A10,1)="5",D10="中国"),1,LEFT(A10,1)="5",60,A10<>0,"NA") -> NA | AF10: =IF(OR(LEFT(A10,1)="4",LEFT(A10,1)="5"),J10,"NA") -> Y01 | AG10: =IF(OR(LEFT(A10,1)="4",LEFT(A10,1)="5"),"ZJ01","NA") -> ZJ01
A11: 400988 | B11: X | C11: 盐酸曲唑酮片/25mg/中国 | D11: 中国 | E11: 何敏迪 | F11: 研发 | G11: Mylan Laboratories Limited | H11: 片 | I11: 1 | J11: Y01 | K11: =_xlfn.IFS(AND(LEFT(A11,1)="4",D11="中国"),"ND",AND(LEFT(A11,1)="5",D11="中国"),"ND",AND(LEFT(A11,1)="5",D11<>"中国"),"M2",A11="","",A11<>"","PD") -> ND | L11: =_xlfn.IFS(LEFT(A11)="1","MB",LEFT(A11)="2","WB",LEFT(A11)="3","WB",AND(LEFT(A11)="4",D11<>"中国",J11<>"Y01"),"FX",A11<>"","EX",A11="","") -> EX | M11: =IF(OR(L11="FX",L11=""),"","NA") -> NA | N11: =IF(A11="","","NA") -> NA | O11: =IF(OR(LEFT(A11,1)="4",LEFT(A11,1)="5"),"NA","") -> NA | P11: =IF(A11="","",IFERROR(VLOOKUP(A11,'表3（采购界面）'!A:J,10,0),"NA")) -> NA | Q11: =IF(A11="","",IFERROR(VLOOKUP(A11,'表3（采购界面）'!A:Z,11,0),"NA")) -> NA | R11: =IF(A11="","",IF(OR(LEFT(A11,1)="1",LEFT(A11,1)="2",LEFT(A11,1)="3"),"F","E")) -> E | S11: =_xlfn.IFS(LEFT(A11,1)="5",VLOOKUP(A11,'表2（QC界面）'!A:J,10,0)+2,LEFT(A11,1)="4",0,AND(LEFT(A11,1)="1",J11<>"Y01"),VLOOKUP(A11,'表2（QC界面）'!A:J,10,0)+24,A11<>0,VLOOKUP(A11,'表2（QC界面）'!A:J,10,0)+4) -> 0 | T11: =IF(OR(LEFT(A11,1)="4",LEFT(A11,1)="5"),"NA",VLOOKUP(A11,'表3（采购界面）'!A:L,12,0)) -> NA | U11: =IF(A11="","","5000-1") -> 5000-1 | V11: =_xlfn.IFS(LEFT(A11,1)="1",2,LEFT(A11,1)="2",1,LEFT(A11,1)="4",1,A11<>0,"NA") -> 1 | W11: =IF(LEFT(A11,1)="4",1,"NA") -> 1 | X11: =_xlfn.IFS(LEFT(A11,1)="4",25,LEFT(A11,1)="5",10,A11<>0,"NA") -> 25 | Y11: =_xlfn.IFS(LEFT(A11,1)="4",10,AND(LEFT(A11,1)="5",D11="中国"),11,LEFT(A11,1)="5",50,A11<>0,"NA") -> 10 | Z11: =IF(AND(LEFT(A11,1)="5",D11="中国"),2,"NA") -> NA | AA11: =_xlfn.IFS(AND(LEFT(A11,1)="5",D11="中国"),2,LEFT(A11,1)="5",1,A11<>0,"NA") -> NA | AB11: =_xlfn.IFS(AND(LEFT(A11,1)="5",D11="中国"),30,LEFT(A11,1)="5",999,A11<>0,"NA") -> NA | AC11: =AB11 -> NA | AD11: =IF(LEFT(A11,1)="5","NA",2) -> 2 | AE11: =_xlfn.IFS(AND(LEFT(A11,1)="5",D11="中国"),1,LEFT(A11,1)="5",60,A11<>0,"NA") -> NA | AF11: =IF(OR(LEFT(A11,1)="4",LEFT(A11,1)="5"),J11,"NA") -> Y01 | AG11: =IF(OR(LEFT(A11,1)="4",LEFT(A11,1)="5"),"ZJ01","NA") -> ZJ01
A12: 400992 | B12: X | C12: 盐酸曲唑酮片/50mg/中国 | E12: 何敏迪 | F12: 研发 | H12: 片 | I12: 1 | J12: Y01 | K12: =_xlfn.IFS(AND(LEFT(A12,1)="4",D12="中国"),"ND",AND(LEFT(A12,1)="5",D12="中国"),"ND",AND(LEFT(A12,1)="5",D12<>"中国"),"M2",A12="","",A12<>"","PD") -> PD | L12: =_xlfn.IFS(LEFT(A12)="1","MB",LEFT(A12)="2","WB",LEFT(A12)="3","WB",AND(LEFT(A12)="4",D12<>"中国",J12<>"Y01"),"FX",A12<>"","EX",A12="","") -> EX | M12: =IF(OR(L12="FX",L12=""),"","NA") -> NA | N12: =IF(A12="","","NA") -> NA | O12: =IF(OR(LEFT(A12,1)="4",LEFT(A12,1)="5"),"NA","") -> NA | P12: =IF(A12="","",IFERROR(VLOOKUP(A12,'表3（采购界面）'!A:J,10,0),"NA")) -> NA | Q12: =IF(A12="","",IFERROR(VLOOKUP(A12,'表3（采购界面）'!A:Z,11,0),"NA")) -> NA | R12: =IF(A12="","",IF(OR(LEFT(A12,1)="1",LEFT(A12,1)="2",LEFT(A12,1)="3"),"F","E")) -> E | S12: =_xlfn.IFS(LEFT(A12,1)="5",VLOOKUP(A12,'表2（QC界面）'!A:J,10,0)+2,LEFT(A12,1)="4",0,AND(LEFT(A12,1)="1",J12<>"Y01"),VLOOKUP(A12,'表2（QC界面）'!A:J,10,0)+24,A12<>0,VLOOKUP(A12,'表2（QC界面）'!A:J,10,0)+4) -> 0 | T12: =IF(OR(LEFT(A12,1)="4",LEFT(A12,1)="5"),"NA",VLOOKUP(A12,'表3（采购界面）'!A:L,12,0)) -> NA | U12: =IF(A12="","","5000-1") -> 5000-1 | V12: =_xlfn.IFS(LEFT(A12,1)="1",2,LEFT(A12,1)="2",1,LEFT(A12,1)="4",1,A12<>0,"NA") -> 1 | W12: =IF(LEFT(A12,1)="4",1,"NA") -> 1 | X12: =_xlfn.IFS(LEFT(A12,1)="4",25,LEFT(A12,1)="5",10,A12<>0,"NA") -> 25 | Y12: =_xlfn.IFS(LEFT(A12,1)="4",10,AND(LEFT(A12,1)="5",D12="中国"),11,LEFT(A12,1)="5",50,A12<>0,"NA") -> 10 | Z12: =IF(AND(LEFT(A12,1)="5",D12="中国"),2,"NA") -> NA | AA12: =_xlfn.IFS(AND(LEFT(A12,1)="5",D12="中国"),2,LEFT(A12,1)="5",1,A12<>0,"NA") -> NA | AB12: =_xlfn.IFS(AND(LEFT(A12,1)="5",D12="中国"),30,LEFT(A12,1)="5",999,A12<>0,"NA") -> NA | AC12: =AB12 -> NA | AD12: =IF(LEFT(A12,1)="5","NA",2) -> 2 | AE12: =_xlfn.IFS(AND(LEFT(A12,1)="5",D12="中国"),1,LEFT(A12,1)="5",60,A12<>0,"NA") -> NA | AF12: =IF(OR(LEFT(A12,1)="4",LEFT(A12,1)="5"),J12,"NA") -> Y01 | AG12: =IF(OR(LEFT(A12,1)="4",LEFT(A12,1)="5"),"ZJ01","NA") -> ZJ01
K17: =_xlfn.IFS(AND(LEFT(A17,1)="4",D17="中国"),"ND",AND(LEFT(A17,1)="5",D17="中国"),"ND",AND(LEFT(A17,1)="5",D17<>"中国"),"M2",A17="","",A17<>"","PD") | L17: =_xlfn.IFS(LEFT(A17)="1","MB",LEFT(A17)="2","WB",LEFT(A17)="3","WB",AND(LEFT(A17)="4",D17<>"中国",J17<>"Y01"),"FX",A17<>"","EX",A17="","") | M17: =IF(OR(L17="FX",L17=""),"","NA") | N17: =IF(A17="","","NA") | O17: =IF(OR(LEFT(A17,1)="4",LEFT(A17,1)="5"),"NA","") | P17: =IF(A17="","",IFERROR(VLOOKUP(A17,'表3（采购界面）'!A:J,10,0),"NA")) | Q17: =IF(A17="","",IFERROR(VLOOKUP(A17,'表3（采购界面）'!A:Z,11,0),"NA")) | R17: =IF(A17="","",IF(OR(LEFT(A17,1)="1",LEFT(A17,1)="2",LEFT(A17,1)="3"),"F","E"))
K18: =_xlfn.IFS(AND(LEFT(A18,1)="4",D18="中国"),"ND",AND(LEFT(A18,1)="5",D18="中国"),"ND",AND(LEFT(A18,1)="5",D18<>"中国"),"M2",A18="","",A18<>"","PD") | L18: =_xlfn.IFS(LEFT(A18)="1","MB",LEFT(A18)="2","WB",LEFT(A18)="3","WB",AND(LEFT(A18)="4",D18<>"中国",J18<>"Y01"),"FX",A18<>"","EX",A18="","") | M18: =IF(OR(L18="FX",L18=""),"","NA") | N18: =IF(A18="","","NA") | O18: =IF(OR(LEFT(A18,1)="4",LEFT(A18,1)="5"),"NA","") | P18: =IF(A18="","",IFERROR(VLOOKUP(A18,'表3（采购界面）'!A:J,10,0),"NA")) | Q18: =IF(A18="","",IFERROR(VLOOKUP(A18,'表3（采购界面）'!A:Z,11,0),"NA")) | R18: =IF(A18="","",IF(OR(LEFT(A18,1)="1",LEFT(A18,1)="2",LEFT(A18,1)="3"),"F","E"))
K19: =_xlfn.IFS(AND(LEFT(A19,1)="4",D19="中国"),"ND",AND(LEFT(A19,1)="5",D19="中国"),"ND",AND(LEFT(A19,1)="5",D19<>"中国"),"M2",A19="","",A19<>"","PD") | L19: =_xlfn.IFS(LEFT(A19)="1","MB",LEFT(A19)="2","WB",LEFT(A19)="3","WB",AND(LEFT(A19)="4",D19<>"中国",J19<>"Y01"),"FX",A19<>"","EX",A19="","") | M19: =IF(OR(L19="FX",L19=""),"","NA") | N19: =IF(A19="","","NA") | O19: =IF(OR(LEFT(A19,1)="4",LEFT(A19,1)="5"),"NA","") | P19: =IF(A19="","",IFERROR(VLOOKUP(A19,'表3（采购界面）'!A:J,10,0),"NA")) | Q19: =IF(A19="","",IFERROR(VLOOKUP(A19,'表3（采购界面）'!A:Z,11,0),"NA")) | R19: =IF(A19="","",IF(OR(LEFT(A19,1)="1",LEFT(A19,1)="2",LEFT(A19,1)="3"),"F","E"))
K20: =_xlfn.IFS(AND(LEFT(A20,1)="4",D20="中国"),"ND",AND(LEFT(A20,1)="5",D20="中国"),"ND",AND(LEFT(A20,1)="5",D20<>"中国"),"M2",A20="","",A20<>"","PD") | L20: =_xlfn.IFS(LEFT(A20)="1","MB",LEFT(A20)="2","WB",LEFT(A20)="3","WB",AND(LEFT(A20)="4",D20<>"中国",J20<>"Y01"),"FX",A20<>"","EX",A20="","") | M20: =IF(OR(L20="FX",L20=""),"","NA") | N20: =IF(A20="","","NA") | O20: =IF(OR(LEFT(A20,1)="4",LEFT(A20,1)="5"),"NA","") | P20: =IF(A20="","",IFERROR(VLOOKUP(A20,'表3（采购界面）'!A:J,10,0),"NA")) | Q20: =IF(A20="","",IFERROR(VLOOKUP(A20,'表3（采购界面）'!A:Z,11,0),"NA")) | R20: =IF(A20="","",IF(OR(LEFT(A20,1)="1",LEFT(A20,1)="2",LEFT(A20,1)="3"),"F","E"))
K21: =_xlfn.IFS(AND(LEFT(A21,1)="4",D21="中国"),"ND",AND(LEFT(A21,1)="5",D21="中国"),"ND",AND(LEFT(A21,1)="5",D21<>"中国"),"M2",A21="","",A21<>"","PD") | L21: =_xlfn.IFS(LEFT(A21)="1","MB",LEFT(A21)="2","WB",LEFT(A21)="3","WB",AND(LEFT(A21)="4",D21<>"中国",J21<>"Y01"),"FX",A21<>"","EX",A21="","") | M21: =IF(OR(L21="FX",L21=""),"","NA") | N21: =IF(A21="","","NA") | O21: =IF(OR(LEFT(A21,1)="4",LEFT(A21,1)="5"),"NA","") | P21: =IF(A21="","",IFERROR(VLOOKUP(A21,'表3（采购界面）'!A:J,10,0),"NA")) | Q21: =IF(A21="","",IFERROR(VLOOKUP(A21,'表3（采购界面）'!A:Z,11,0),"NA")) | R21: =IF(A21="","",IF(OR(LEFT(A21,1)="1",LEFT(A21,1)="2",LEFT(A21,1)="3"),"F","E"))
K22: =_xlfn.IFS(AND(LEFT(A22,1)="4",D22="中国"),"ND",AND(LEFT(A22,1)="5",D22="中国"),"ND",AND(LEFT(A22,1)="5",D22<>"中国"),"M2",A22="","",A22<>"","PD") | L22: =_xlfn.IFS(LEFT(A22)="1","MB",LEFT(A22)="2","WB",LEFT(A22)="3","WB",AND(LEFT(A22)="4",D22<>"中国",J22<>"Y01"),"FX",A22<>"","EX",A22="","") | M22: =IF(OR(L22="FX",L22=""),"","NA") | N22: =IF(A22="","","NA") | O22: =IF(OR(LEFT(A22,1)="4",LEFT(A22,1)="5"),"NA","") | P22: =IF(A22="","",IFERROR(VLOOKUP(A22,'表3（采购界面）'!A:J,10,0),"NA")) | Q22: =IF(A22="","",IFERROR(VLOOKUP(A22,'表3（采购界面）'!A:Z,11,0),"NA")) | R22: =IF(A22="","",IF(OR(LEFT(A22,1)="1",LEFT(A22,1)="2",LEFT(A22,1)="3"),"F","E"))
K23: =_xlfn.IFS(AND(LEFT(A23,1)="4",D23="中国"),"ND",AND(LEFT(A23,1)="5",D23="中国"),"ND",AND(LEFT(A23,1)="5",D23<>"中国"),"M2",A23="","",A23<>"","PD") | L23: =_xlfn.IFS(LEFT(A23)="1","MB",LEFT(A23)="2","WB",LEFT(A23)="3","WB",AND(LEFT(A23)="4",D23<>"中国",J23<>"Y01"),"FX",A23<>"","EX",A23="","") | M23: =IF(OR(L23="FX",L23=""),"","NA") | N23: =IF(A23="","","NA") | O23: =IF(OR(LEFT(A23,1)="4",LEFT(A23,1)="5"),"NA","") | P23: =IF(A23="","",IFERROR(VLOOKUP(A23,'表3（采购界面）'!A:J,10,0),"NA")) | Q23: =IF(A23="","",IFERROR(VLOOKUP(A23,'表3（采购界面）'!A:Z,11,0),"NA")) | R23: =IF(A23="","",IF(OR(LEFT(A23,1)="1",LEFT(A23,1)="2",LEFT(A23,1)="3"),"F","E"))
K24: =_xlfn.IFS(AND(LEFT(A24,1)="4",D24="中国"),"ND",AND(LEFT(A24,1)="5",D24="中国"),"ND",AND(LEFT(A24,1)="5",D24<>"中国"),"M2",A24="","",A24<>"","PD") | L24: =_xlfn.IFS(LEFT(A24)="1","MB",LEFT(A24)="2","WB",LEFT(A24)="3","WB",AND(LEFT(A24)="4",D24<>"中国",J24<>"Y01"),"FX",A24<>"","EX",A24="","") | M24: =IF(OR(L24="FX",L24=""),"","NA") | N24: =IF(A24="","","NA") | O24: =IF(OR(LEFT(A24,1)="4",LEFT(A24,1)="5"),"NA","") | P24: =IF(A24="","",IFERROR(VLOOKUP(A24,'表3（采购界面）'!A:J,10,0),"NA")) | Q24: =IF(A24="","",IFERROR(VLOOKUP(A24,'表3（采购界面）'!A:Z,11,0),"NA")) | R24: =IF(A24="","",IF(OR(LEFT(A24,1)="1",LEFT(A24,1)="2",LEFT(A24,1)="3"),"F","E"))
K25: =_xlfn.IFS(AND(LEFT(A25,1)="4",D25="中国"),"ND",AND(LEFT(A25,1)="5",D25="中国"),"ND",AND(LEFT(A25,1)="5",D25<>"中国"),"M2",A25="","",A25<>"","PD") | L25: =_xlfn.IFS(LEFT(A25)="1","MB",LEFT(A25)="2","WB",LEFT(A25)="3","WB",AND(LEFT(A25)="4",D25<>"中国",J25<>"Y01"),"FX",A25<>"","EX",A25="","") | M25: =IF(OR(L25="FX",L25=""),"","NA") | N25: =IF(A25="","","NA") | O25: =IF(OR(LEFT(A25,1)="4",LEFT(A25,1)="5"),"NA","") | P25: =IF(A25="","",IFERROR(VLOOKUP(A25,'表3（采购界面）'!A:J,10,0),"NA")) | Q25: =IF(A25="","",IFERROR(VLOOKUP(A25,'表3（采购界面）'!A:Z,11,0),"NA")) | R25: =IF(A25="","",IF(OR(LEFT(A25,1)="1",LEFT(A25,1)="2",LEFT(A25,1)="3"),"F","E"))
K26: =_xlfn.IFS(AND(LEFT(A26,1)="4",D26="中国"),"ND",AND(LEFT(A26,1)="5",D26="中国"),"ND",AND(LEFT(A26,1)="5",D26<>"中国"),"M2",A26="","",A26<>"","PD") | L26: =_xlfn.IFS(LEFT(A26)="1","MB",LEFT(A26)="2","WB",LEFT(A26)="3","WB",AND(LEFT(A26)="4",D26<>"中国",J26<>"Y01"),"FX",A26<>"","EX",A26="","") | M26: =IF(OR(L26="FX",L26=""),"","NA") | N26: =IF(A26="","","NA") | O26: =IF(OR(LEFT(A26,1)="4",LEFT(A26,1)="5"),"NA","") | P26: =IF(A26="","",IFERROR(VLOOKUP(A26,'表3（采购界面）'!A:J,10,0),"NA")) | Q26: =IF(A26="","",IFERROR(VLOOKUP(A26,'表3（采购界面）'!A:Z,11,0),"NA")) | R26: =IF(A26="","",IF(OR(LEFT(A26,1)="1",LEFT(A26,1)="2",LEFT(A26,1)="3"),"F","E"))
K27: =_xlfn.IFS(AND(LEFT(A27,1)="4",D27="中国"),"ND",AND(LEFT(A27,1)="5",D27="中国"),"ND",AND(LEFT(A27,1)="5",D27<>"中国"),"M2",A27="","",A27<>"","PD") | L27: =_xlfn.IFS(LEFT(A27)="1","MB",LEFT(A27)="2","WB",LEFT(A27)="3","WB",AND(LEFT(A27)="4",D27<>"中国",J27<>"Y01"),"FX",A27<>"","EX",A27="","") | M27: =IF(OR(L27="FX",L27=""),"","NA") | N27: =IF(A27="","","NA") | O27: =IF(OR(LEFT(A27,1)="4",LEFT(A27,1)="5"),"NA","") | P27: =IF(A27="","",IFERROR(VLOOKUP(A27,'表3（采购界面）'!A:J,10,0),"NA")) | Q27: =IF(A27="","",IFERROR(VLOOKUP(A27,'表3（采购界面）'!A:Z,11,0),"NA")) | R27: =IF(A27="","",IF(OR(LEFT(A27,1)="1",LEFT(A27,1)="2",LEFT(A27,1)="3"),"F","E"))
K28: =_xlfn.IFS(AND(LEFT(A28,1)="4",D28="中国"),"ND",AND(LEFT(A28,1)="5",D28="中国"),"ND",AND(LEFT(A28,1)="5",D28<>"中国"),"M2",A28="","",A28<>"","PD") | L28: =_xlfn.IFS(LEFT(A28)="1","MB",LEFT(A28)="2","WB",LEFT(A28)="3","WB",AND(LEFT(A28)="4",D28<>"中国",J28<>"Y01"),"FX",A28<>"","EX",A28="","") | M28: =IF(OR(L28="FX",L28=""),"","NA") | N28: =IF(A28="","","NA") | O28: =IF(OR(LEFT(A28,1)="4",LEFT(A28,1)="5"),"NA","") | P28: =IF(A28="","",IFERROR(VLOOKUP(A28,'表3（采购界面）'!A:J,10,0),"NA")) | Q28: =IF(A28="","",IFERROR(VLOOKUP(A28,'表3（采购界面）'!A:Z,11,0),"NA")) | R28: =IF(A28="","",IF(OR(LEFT(A28,1)="1",LEFT(A28,1)="2",LEFT(A28,1)="3"),"F","E"))
... K999: =_xlfn.IFS(AND(LEFT(A999,1)="4",D999="中国"),"ND",AND(LEFT(A999,1)="5",D999="中国"),"ND",AND(LEFT(A999,1)="5",D999<>"中国"),"M2",A999="","",A999<>"","PD") | L999: =_xlfn.IFS(LEFT(A999)="1","MB",LEFT(A999)="2","WB",LEFT(A999)="3","WB",AND(LEFT(A999)="4",D999<>"中国",J999<>"Y01"),"FX",A999<>"","EX",A999="","") | M999: =IF(OR(L999="FX",L999=""),"","NA") | N999: =IF(A999="","","NA") | O999: =IF(OR(LEFT(A999,1)="4",LEFT(A999,1)="5"),"NA","") | P999: =IF(A999="","",IFERROR(VLOOKUP(A999,'表3（采购界面）'!A:J,10,0),"NA")) | Q999: =IF(A999="","",IFERROR(VLOOKUP(A999,'表3（采购界面）'!A:Z,11,0),"NA")) | R999: =IF(A999="","",IF(OR(LEFT(A999,1)="1",LEFT(A999,1)="2",LEFT(A999,1)="3"),"F","E"))

Sheet Sheet4
A1: 44152 | B1: =A1/$D$1*$E$1 -> 250845.88 | D1: =SUM(A1:A12) -> 533458 | E1: 3030796.8
A2: 44737 | B2: =A2/$D$1*$E$1 -> 254169.5 | H2: 9940 | I2: =H2/$J$2*$K$2 -> 62927.557 | J2: =SUM(H2:H4) -> 107010 | K2: 677452.5
A3: 44047 | B3: =A3/$D$1*$E$1 -> 250249.33 | H3: 45030 | I3: =H3/$J$2*$K$2 -> 285073.23
A4: 44407 | B4: =A4/$D$1*$E$1 -> 252294.64 | H4: 52040 | I4: =H4/$J$2*$K$2 -> 329451.72
A5: 44985 | B5: =A5/$D$1*$E$1 -> 255578.5
A6: 44730 | B6: =A6/$D$1*$E$1 -> 254129.73
A7: 44355 | B7: =A7/$D$1*$E$1 -> 251999.2
A8: 43545 | B8: =A8/$D$1*$E$1 -> 247397.26
A9: 44520 | B9: =A9/$D$1*$E$1 -> 252936.64 | H9: 9940 | I9: =H9/$J$9*$K$9 -> 97552.74 | J9: =SUM(H9:H11) -> 9940 | K9: 97552.74
A10: 44730 | B10: =A10/$D$1*$E$1 -> 254129.73
A11: 44745 | B11: =A11/$D$1*$E$1 -> 254214.96
A12: 44505 | B12: =A12/$D$1*$E$1 -> 252851.42
H13: 48900 | I13: =H13/$J$13*$K$13 -> 134150.44 | J13: =SUM(H13:H15) -> 111670 | K13: 306351.33
H14: 48600 | I14: =H14/$J$13*$K$13 -> 133327.43
H15: 14170 | I15: =H15/$J$13*$K$13 -> 38873.452
G21: 1 | H21: 97552.74 | I21: 9940 | J21: 9.81 | K21: 11.09 | L21: 盒 | M21: 4500041720 | N21: 30 | O21: 盐酸帕罗西汀片/20mg/10片/板×3板/盒×200盒/箱/中国
G22: 2 | H22: 134150.44 | I22: 48900 | J22: 2.74 | K22: 3.1 | L22: 盒 | M22: 4500040605 | N22: 10 | O22: 利培酮片/1mg/10片/板×6板/盒×150盒/箱/中国
G23: 3 | H23: 133327.43 | I23: 48600 | J23: 2.74 | K23: 3.1 | L23: 盒 | M23: 4500040605 | N23: 10 | O23: 利培酮片/1mg/10片/板×6板/盒×150盒/箱/中国
G24: 4 | H24: 38873.452 | I24: 14170 | J24: 2.74 | K24: 3.1 | L24: 盒 | M24: 4500040605 | N24: 10 | O24: 利培酮片/1mg/10片/板×6板/盒×150盒/箱/中国

Sheet Sheet3
A1: 物料 | B1: 物料描述 | C1: 内部批号 | D1: 质量检验 | E1: 销售订单 | F1: 客户合同号 | G1: 生产日期 | H1: 有效期至
A2: 500104 | B2: 盐酸苯那普利片/20mg/30片/瓶/美国 | C2: 0000048293 | D2: 43053 | E2: 2200001199 | F2: 4500006264 | G2: 44793 | H2: 45524 | I2: 2200001199 | J2: 20 | K2: 2200001570 | L2: 10
A3: 500104 | B3: 盐酸苯那普利片/20mg/30片/瓶/美国 | C3: 0000048293 | D3: 42240 | I3: 2200001199 | J3: 20 | K3: 2200001549 | L3: 20
A4: 500103 | B4: 盐酸苯那普利片/20mg/100片/瓶/美国 | C4: 0000048294 | D4: 25558 | E4: 2200001199 | F4: 4500006264 | G4: 44795 | H4: 45891 | I4: 2200001199 | J4: 30 | K4: 2200001549 | L4: 30
A5: 500107 | B5: 盐酸苯那普利片/40mg/30片/瓶/美国 | C5: 0000048794 | D5: 85100 | E5: 2200001199 | F5: 4500006264 | G5: 44795 | H5: 45526 | I5: 2200001199 | J5: 40 | K5: 2200001549 | L5: 40
A6: 500106 | B6: 盐酸苯那普利片/40mg/100片/瓶/美国 | C6: 0000048795 | D6: 25440 | E6: 2200001199 | F6: 4500006264 | G6: 44796 | H6: 45506 | I6: 2200001199 | J6: 50 | K6: 2200001549 | L6: 50

Sheet Sheet1
A3: API | B3: 100343
A4: 辅料 | B4: 11965
A5: 包材 | B5: 20212

Sheet Sheet2
A1: 物料名称 | B1: 规格 | C1: 厂家 | D1: 年前 | E1: 预算 | F1: 最新 | G1: 年初预计使用量 | H1: 年初预计半年度使用量 | I1: 已使用 | J1: 库存 | K1: 预计仍需使用 | L1: 预计仍需使用 | M1: 影响预算金额 | N1: 影响预算金额
D2: 价格 | E2: 价格 | F2: 价格 | G2: (KG) | H2: (KG) | I2: (KG) | J2: (KG) | K2: 上半年 | L2: 下半年 | M2: 上半年 | N2: 下半年
D3: (元/kg） | E3: (元/kg) | F3: (元/kg) | K3: （KG） | L3: （KG） | M3: （万元） | N3: （万元）
A4: 单水乳糖 | B4: Flowlac | C4: MEGGLE | D4: 31.85 | E4: 31.85 | F4: 36.3 | G4: 140569 | H4: 52763 | I4: 28000 | J4: 19886 | K4: =H4-I4-J4 -> 4877 | L4: =G4-I4-J4-K4 -> 87806 | M4: =K4*($F4-$E4)/10000 -> 2.170265 | N4: =L4*($F4-$E4)/10000 -> 39.07367 | O4: 42.6 | P4: =M4+N4 -> 41.243935
A5: 甘露醇 | B5: 160C | C5: Roquette | D5: 55 | E5: 55 | F5: 60 | G5: 114572 | H5: 58093 | I5: 17208 | J5: 29468 | K5: =H5-I5-J5 -> 11417 | L5: =G5-I5-J5-K5 -> 56479 | M5: =K5*(F5-E5)/10000 -> 5.7085 | N5: =L5*($F5-$E5)/10000 -> 28.2395 | O5: 33.9 | P5: =M5+N5 -> 33.948
A6: 微晶纤维素 | B6: 101/102 | C6: JRS | D6: 39.9 | E6: 41.9 | F6: 42.9 | G6: 309405 | H6: 125889 | I6: 48314 | J6: 85412 | K6: 0 | L6: =G6-I6-J6-K6 -> 175679 | M6: =K6*(F6-E6)/10000 -> 0 | N6: =L6*($F6-$E6)/10000 -> 17.5679 | O6: 17.6 | P6: =M6+N6 -> 17.5679
A7: 交联聚维酮 | B7: Kollidon CL | C7: BASF | D7: 200 | E7: 173 | F7: 230 | G7: 6715 | H7: 2935 | I7: 458 | J7: 4502 | K7: 0 | L7: =G7-I7-J7-K7 -> 1755 | M7: =K7*(F7-E7)/10000 -> 0 | N7: =L7*($F7-$E7)/10000 -> 10.0035 | O7: 10 | P7: =M7+N7 -> 10.0035
A8: 甘露醇 | B8: 200SD | C8: Roquette | D8: 120 | E8: 120 | F8: 128 | G8: 17425 | H8: 8690 | I8: 1277 | J8: 3749 | K8: =H8-I8-J8 -> 3664 | L8: =G8-I8-J8-K8 -> 8735 | M8: =K8*(F8-E8)/10000 -> 2.9312 | N8: =L8*($F8-$E8)/10000 -> 6.988 | O8: 9.9 | P8: =M8+N8 -> 9.9192
A9: 聚维酮 | B9: K30 | C9: BASF | D9: 196 | E9: 179 | F9: 208 | G9: 4802 | H9: 2253 | I9: 98 | J9: 2127 | K9: =H9-I9-J9 -> 28 | L9: =G9-I9-J9-K9 -> 2549 | M9: =K9*(F9-E9)/10000 -> 0.0812 | N9: =L9*($F9-$E9)/10000 -> 7.3921 | O9: 7.5 | P9: =M9+N9 -> 7.4733
A10: 玉米淀粉 | B10: —— | C10: Roquette | D10: 13.5 | E10: 14 | F10: 16 | G10: 24126 | H10: 12379 | I10: 1050 | J10: 9012 | K10: =H10-I10-J10 -> 2317 | L10: =G10-I10-J10-K10 -> 11747 | M10: =K10*(F10-E10)/10000 -> 0.4634 | N10: =L10*($F10-$E10)/10000 -> 2.3494 | O10: 2.8 | P10: =M10+N10 -> 2.8128
A11: 泊洛沙姆 | B11: —— | C11: BASF | D11: 1350 | E11: 1250 | F11: 1650 | G11: 50 | H11: 50 | I11: 24 | J11: 1.2 | K11: =H11-I11-J11 -> 24.8 | L11: =G11-I11-J11-K11 -> 0 | M11: =K11*(F11-E11)/10000 -> 0.992 | N11: =L11*($F11-$E11)/10000 -> 0 | O11: 2 | P11: =M11+N11 -> 0.992
A12: 合计 | M12: =SUM(M4:M11) -> 12.346565 | N12: =SUM(N4:N11) -> 111.61407 | O12: 124

Sheet Sheet6
C1: 产品名称 | D1: 物料名称 | E1: 变更前代号 | F1: 厂家 | G1: 变更后代号 | H1: 厂家 | I1: 已变更产品
C2: 氯沙坦钾片 | D2: 单水乳糖 | E2: 100042 | F2: DFE | G2: 101624 | H2: 道宁 | I2: 草酸US
D3: 微晶纤维素 | E3: 100382 | F3: 明台 | G3: 101516 | H3: 常州JRS | I3: 舍曲林CHN 德国JRS换常州JRS
D4: 预胶化淀粉 | E4: 100041 | F4: Colorcon (IN) | G4: 101939 | H4: 山河 | I4: 复方氯沙CHN
D5: 硬脂酸镁 | E5: 100018 | F5: Merck | G5: 101182 | H5: Peter Greven | I5: 缬沙坦US
C6: 福辛普利钠片 | D6: 微晶纤维素 | E6: 100008 | F6: 杜邦
D7: 单水乳糖 | E7: 100038 | F7: DFE | G7: 101482 | H7: 道宁 | I7: 利培酮片US
D8: 交联聚维酮 | E8: 100094
D9: 聚维酮 | E9: 100057
D10: 硬脂富马酸钠 | E10: 100128

Sheet Sheet5
A1: 1 | B1: 250845.88 | C1: 44152 | D1: =C1/$E$1*$F$1 -> 250845.88 | E1: =SUM(C1:C12) -> 533458 | F1: 3030796.8 | G1: 13 | H1: 63105.04 | I1: 6430 | J1: =I1/$K$1*$L$1-H1 -> 0.0042335584 | K1: =SUM(I1:I27) -> 679830 | L1: 6671959.9
A2: 2 | B2: 254169.5 | C2: 44737 | D2: =C2/$E$1*$F$1 -> 254169.5 | G2: 14 | H2: 256738.41 | I2: 26160 | J2: =I2/$K$1*$L$1-H2 -> -0.0029782446
A3: 3 | B3: 250249.33 | C3: 44047 | D3: =C3/$E$1*$F$1 -> 250249.33 | G3: 15 | H3: 255560.71 | I3: 26040 | J3: =I3/$K$1*$L$1-H3 -> -0.0020930232
A4: 4 | B4: 252294.64 | C4: 44407 | D4: =C4/$E$1*$F$1 -> 252294.64 | G4: 16 | H4: 254383.01 | I4: 25920 | J4: =I4/$K$1*$L$1-H4 -> -0.0012078019
A5: 5 | B5: 255578.5 | C5: 44985 | D5: =C5/$E$1*$F$1 -> 255578.5 | G5: 17 | H5: 256345.84 | I5: 26120 | J5: =I5/$K$1*$L$1-H5 -> 0.00065016255
A6: 6 | B6: 254129.73 | C6: 44730 | D6: =C6/$E$1*$F$1 -> 254129.73 | G6: 18 | H6: 250849.91 | I6: 25560 | J6: =I6/$K$1*$L$1-H6 -> 0.001447862
A7: 7 | B7: 251999.2 | C7: 44355 | D7: =C7/$E$1*$F$1 -> 251999.2 | G7: 19 | H7: 251929.47 | I7: 25670 | J7: =I7/$K$1*$L$1-H7 -> -0.0010302576
A8: 8 | B8: 247397.26 | C8: 43545 | D8: =C8/$E$1*$F$1 -> 247397.26 | G8: 20 | H8: 255855.13 | I8: 26070 | J8: =I8/$K$1*$L$1-H8 -> 0.0026856714
A9: 9 | B9: 252936.64 | C9: 44520 | D9: =C9/$E$1*$F$1 -> 252936.64 | G9: 21 | H9: 252910.88 | I9: 25770 | J9: =I9/$K$1*$L$1-H9 -> 0.0048987247
A10: 10 | B10: 254129.73 | C10: 44730 | D10: =C10/$E$1*$F$1 -> 254129.73 | G10: 22 | H10: 255364.42 | I10: 26020 | J10: =I10/$K$1*$L$1-H10 -> 0.0047211803
A11: 11 | B11: 254214.96 | C11: 44745 | D11: =C11/$E$1*$F$1 -> 254214.96 | G11: 23 | H11: 255168.14 | I11: 26000 | J11: =I11/$K$1*$L$1-H11 -> 0.0015353838
A12: 12 | B12: 252851.42 | C12: 44505 | D12: =C12/$E$1*$F$1 -> 252851.42 | G12: 24 | H12: 252616.46 | I12: 25740 | J12: =I12/$K$1*$L$1-H12 -> 0.00012003002
G13: 25 | H13: 253499.73 | I13: 25830 | J13: =I13/$K$1*$L$1-H13 -> 0.004456114
G14: 26 | H14: 255855.13 | I14: 26070 | J14: =I14/$K$1*$L$1-H14 -> 0.0026856714
G15: 27 | H15: 252420.18 | I15: 25720 | J15: =I15/$K$1*$L$1-H15 -> -0.0030657664
G16: 28 | H16: 255266.28 | I16: 26010 | J16: =I16/$K$1*$L$1-H16 -> 0.0031282821
G17: 29 | H17: 254579.29 | I17: 25940 | J17: =I17/$K$1*$L$1-H17 -> 0.0019779945
G18: 30 | H18: 254873.72 | I18: 25970 | J18: =I18/$K$1*$L$1-H18 -> -0.0032433108
G19: 31 | H19: 253303.45 | I19: 25810 | J19: =I19/$K$1*$L$1-H19 -> 0.0012703176
G20: 32 | H20: 255168.14 | I20: 26000 | J20: =I20/$K$1*$L$1-H20 -> 0.0015353838
G21: 33 | H21: 256149.56 | I21: 26100 | J21: =I21/$K$1*$L$1-H21 -> -0.0025356339
G22: 34 | H22: 254284.87 | I22: 25910 | J22: =I22/$K$1*$L$1-H22 -> -0.0028007002
G23: 35 | H23: 253990.44 | I23: 25880 | J23: =I23/$K$1*$L$1-H23 -> 0.0024206051
G24: 36 | H24: 251144.34 | I24: 25590 | J24: =I24/$K$1*$L$1-H24 -> -0.0037734433
... G27: 39 | H27: 252518.32 | I27: 25730 | J27: =I27/$K$1*$L$1-H27 -> -0.0014728682
